{
    "RequestHeader": {
        "requestID": "___timestamp___",
        "action": "getIssurance",
        "channel": "SBIGIC",
        "transactionTimestamp": "___transactionTimestamp___"
    },
    "RequestBody": {
        "QuotationNo": "___dbmaster_insurer_transaction_identifier___",
        "Amount": "",
        "CurrencyId": 1,
        "PayMode": 212,
        "FeeType": 11,
        "Payer": "payer",
        "TransactionDate": "___payment_date___T23:59:59",
        "PaymentReferNo": "___pay_id___",
        "InstrumentNumber": "___pay_id___",
        "InstrumentDate": "___payment_date___",
        "BankCode": "2",
        "BankName": "STATE BANK OF INDIA",
        "BankBranchName": "",
        "BankBranchCode": "",
        "LocationType": "2",
        "RemitBankAccount": "30",
        "ReceiptCreatedBy": "",
        "PickupDate": "___payment_date___",
        "IFSCCode": "",
        "MICRNumber": "",
        "PANNumber": "",
        "ReceiptBranch": "",
        "ReceiptTransactionDate": "___payment_date___",
        "ReceiptDate": "___payment_date___",
        "EscalationDepartment": "",
        "Comment": "",
        "AccountNumber": "",
        "AccountName": ""
    }
}